{
	"configurations" : 
	[
		{
			"directories" : 
			[
				{
					"build" : ".",
					"hasInstallRule" : true,
					"jsonFile" : "directory-.-Debug-0caa670b10a6634f3605.json",
					"minimumCMakeVersion" : 
					{
						"string" : "3.16"
					},
					"projectIndex" : 0,
					"source" : ".",
					"targetIndexes" : 
					[
						0,
						1,
						2
					]
				}
			],
			"name" : "Debug",
			"projects" : 
			[
				{
					"directoryIndexes" : 
					[
						0
					],
					"name" : "client",
					"targetIndexes" : 
					[
						0,
						1,
						2
					]
				}
			],
			"targets" : 
			[
				{
					"directoryIndex" : 0,
					"id" : "client::@6890427a1f51a3e7e1df",
					"jsonFile" : "target-client-Debug-f6535decb1b27ffcbae1.json",
					"name" : "client",
					"projectIndex" : 0
				},
				{
					"directoryIndex" : 0,
					"id" : "client_autogen::@6890427a1f51a3e7e1df",
					"jsonFile" : "target-client_autogen-Debug-d41cd90d633dfc3a5bd9.json",
					"name" : "client_autogen",
					"projectIndex" : 0
				},
				{
					"directoryIndex" : 0,
					"id" : "client_autogen_timestamp_deps::@6890427a1f51a3e7e1df",
					"jsonFile" : "target-client_autogen_timestamp_deps-Debug-da2791d42607a0bb4c28.json",
					"name" : "client_autogen_timestamp_deps",
					"projectIndex" : 0
				}
			]
		}
	],
	"kind" : "codemodel",
	"paths" : 
	{
		"build" : "C:/Users/1/Desktop/cheezyRat/client/build/Desktop_Qt_6_11_0_MSVC2022_64bit-u041eu0442u043bu0430u0434u043au0430",
		"source" : "C:/Users/1/Desktop/cheezyRat/client"
	},
	"version" : 
	{
		"major" : 2,
		"minor" : 7
	}
}
